ticketrenderer/__init__.py
ticketrenderer/tests.py
ticketrenderer/ticketrenderer.py
ticketrenderer-0.3.0.dist-info/LICENSE.txt
ticketrenderer-0.3.0.dist-info/METADATA
ticketrenderer-0.3.0.dist-info/WHEEL
ticketrenderer-0.3.0.dist-info/top_level.txt
ticketrenderer-0.3.0.dist-info/RECORD
